[
    {"general": [
        "sex", "nude", "porn", "bạo lực", "đẫm máu", "tránh thai", "trộm", "cướp", "hiếp", "giết", "lộ hàng", "tự tử",
        "trả thù", "gay", "dượng", "đồng tính", "valentin", "thủ dâm", "tự sướng", "quay tay", "chim", "dái", "cặc", "lồn",
        "địt", "cương cứng", "nứng", "fuck", "step", "tỏ tình", "yêu sớm", "thụ tinh", "tinh trùng", "rụng trứng", "ẩn danh",
        "lừa đảo"
    ]},
    {
        "notAllowed": [],
        "telegramId": "",
        "computerId": "4C4C4544-0048-5610-805A-C7C04F585932",
        "name": "Thanh Giang",
        "prevent": [23, 0, 1, 2, 3, 4],
        "password": "huybolenh"
    },
    {
        "notAllowed": [],
        "telegramId": "",
        "computerId": "03000200-0400-0500-0006-000700080009",
        "name": "Xeon Thin PC",
        "prevent": [23, 0, 1, 2, 3, 4],
        "password": "huybolenh"
    }
]
